CHANGELOG.md
CONTRIBUTING.md
LICENSE
MANIFEST.in
README.en.md
README.md
setup.py
src/yandex_checkout_payout/__init__.py
src/yandex_checkout_payout/__main__.py
src/yandex_checkout_payout/cli.py
src/yandex_checkout_payout/configuration.py
src/yandex_checkout_payout/payout.py
src/yandex_checkout_payout/py.typed
src/yandex_checkout_payout.egg-info/PKG-INFO
src/yandex_checkout_payout.egg-info/SOURCES.txt
src/yandex_checkout_payout.egg-info/dependency_links.txt
src/yandex_checkout_payout.egg-info/entry_points.txt
src/yandex_checkout_payout.egg-info/not-zip-safe
src/yandex_checkout_payout.egg-info/requires.txt
src/yandex_checkout_payout.egg-info/top_level.txt
src/yandex_checkout_payout/artefacts/__init__.py
src/yandex_checkout_payout/artefacts/deposit.cer
src/yandex_checkout_payout/domain/__init__.py
src/yandex_checkout_payout/domain/common/__init__.py
src/yandex_checkout_payout/domain/common/base_object.py
src/yandex_checkout_payout/domain/common/cli_client.py
src/yandex_checkout_payout/domain/common/client.py
src/yandex_checkout_payout/domain/common/context.py
src/yandex_checkout_payout/domain/common/currency.py
src/yandex_checkout_payout/domain/common/data_context.py
src/yandex_checkout_payout/domain/common/error_converter.py
src/yandex_checkout_payout/domain/common/generator_csr.py
src/yandex_checkout_payout/domain/common/http_verb.py
src/yandex_checkout_payout/domain/common/keychain.py
src/yandex_checkout_payout/domain/common/openssl_helper.py
src/yandex_checkout_payout/domain/common/xml_helper.py
src/yandex_checkout_payout/domain/exceptions/__init__.py
src/yandex_checkout_payout/domain/exceptions/api_error.py
src/yandex_checkout_payout/domain/exceptions/authorize_error.py
src/yandex_checkout_payout/domain/exceptions/bad_request_error.py
src/yandex_checkout_payout/domain/exceptions/forbidden_error.py
src/yandex_checkout_payout/domain/exceptions/not_found_error.py
src/yandex_checkout_payout/domain/exceptions/open_ssl_error.py
src/yandex_checkout_payout/domain/exceptions/response_processing_error.py
src/yandex_checkout_payout/domain/exceptions/too_many_request_error.py
src/yandex_checkout_payout/domain/exceptions/unauthorized_error.py
src/yandex_checkout_payout/domain/models/__init__.py
src/yandex_checkout_payout/domain/models/organization.py
src/yandex_checkout_payout/domain/models/recipients/__init__.py
