Metadata-Version: 2.1
Name: yandex-checkout-payout
Version: 1.0.1
Summary: UNKNOWN
Home-page: https://github.com/yandex-money/yandex-checkout-payout-sdk-python
Author: Yandex Money
Author-email: cms@yamoney.ru
License: MIT license
Keywords: yandex,checkout,payout,sdk,python
Platform: UNKNOWN
Classifier: License :: OSI Approved :: MIT License
Classifier: Natural Language :: Russian
Classifier: Programming Language :: Python :: 3.5
Classifier: Programming Language :: Python :: 3.6
Classifier: Programming Language :: Python :: 3.7
Classifier: Programming Language :: Python :: 3.8
Requires-Python: >=3.5
